fidlyai/__init__.py
fidlyai/gemini.py
fidlyai-1.1.1.dist-info/METADATA
fidlyai-1.1.1.dist-info/WHEEL
fidlyai-1.1.1.dist-info/top_level.txt
fidlyai-1.1.1.dist-info/RECORD
