Metadata-Version: 2.4
Name: fidlyai
Version: 1.1.1
Summary: FidlyAI is a highly effective AI package for Python, designed to be user-friendly.
Home-page: https://mrfidal.in/package/py/fidlyai
Author: Fidal PalamParambil
Author-email: mrfidal@proton.me
Keywords: gemini,fidlyai,google gemini,gemini ai,ai wrapper,gemini api,google ai,fidal,mr fidal,python ai,multi-user ai,ask gemini,chat gemini,bulk prompts,gemini python wrapper
Classifier: Programming Language :: Python :: 3
Classifier: License :: OSI Approved :: MIT License
Classifier: Operating System :: OS Independent
Requires-Python: >=3.6
Requires-Dist: requests
Dynamic: author
Dynamic: author-email
Dynamic: classifier
Dynamic: description
Dynamic: description-content-type
Dynamic: home-page
Dynamic: keywords
Dynamic: requires-dist
Dynamic: requires-python
Dynamic: summary
